Workbook

Sheet Resumo
A1: Banheiro | materiais e peças
A2: MAXHAUS | R2 | 25/10/2026 | valores em R$ | conferir em obra
A4: Categoria | B4: Total R$
A5: Revestimentos | B5: =SUMIF(Orcamento!A5:A60,A5,Orcamento!F5:F60) -> 9524.65
A6: Louças e metais | B6: =SUMIF(Orcamento!A5:A60,A6,Orcamento!F5:F60) -> 8060.22
A7: Ralos e esgoto | B7: =SUMIF(Orcamento!A5:A60,A7,Orcamento!F5:F60) -> 1173
A8: Água quente/fria | B8: =SUMIF(Orcamento!A5:A60,A8,Orcamento!F5:F60) -> 812
A9: Impermeabilização | B9: =SUMIF(Orcamento!A5:A60,A9,Orcamento!F5:F60) -> 667.6
A10: Subtotal | B10: =SUM(B5:B9) -> 20237.47
A11: Contingência | B11: 0.15
A12: Reserva financeira R$ | B12: =B10*B11 -> 3035.6205
A13: Total com contingência | B13: =B10+B12 -> 23273.09
A14: Excluídos: piso Monofloor Everest, elétrica/iluminação, mão de obra, argamassa colante (empreiteira), logística (frete, entrega e subida no condomínio, caçamba de entulho) e pintura da faixa de 38 mm acima do revestimento.
A15: Reserva de 15% apresentada à parte; não é custo contratado.
A18: Preço cotado = apenas Bleu Nuit; demais preços: web, referência ou estimativa.
A19: Orçamento restrito ao banheiro. Hídrica/cozinha excluído.
A20: R2: paginação refeita (peças inteiras, topo a 2.353 mm, pontas simétricas), compra por área + 10%, argamassa com a empreiteira, impermeabilização incluída e sobreposições resolvidas.

Sheet Orcamento
A1: Orçamento detalhado
A2: MAXHAUS | R2 | 25/10/2026 | valores em R$ | conferir em obra
A4: Grupo | B4: Item | C4: Un. | D4: Quantidade | E4: R$/un. | F4: Total R$ | G4: Origem preço | H4: Critério / pendência | I4: Fonte
A5: Revestimentos | B5: Gouache Bleu Nuit 7,5x15,5 BR BOLD | C5: cx | D5: =Quantidades!G5 -> 63 | E5: 101.997 | F5: =ROUND(D5*E5,2) -> 6425.81 | G5: Cotado | H5: Área revestida 16,95 m² + 10% = 18,65 m², caixa de 0,30 m² / 26 peças. Cobre as 1480 peças físicas da paginação R2 com 11% de folga. | I5: Proposta Portobello 05310148, 13/10/2026, arquivo sem sufixo; validade 31/10/2026
A6: Revestimentos | B6: Gouache Nuage 7,5x15,5 BR BOLD | C6: cx | D6: =Quantidades!G6 -> 7 | E6: 101.997 | F6: =ROUND(D6*E6,2) -> 713.98 | G6: Estimativa | H6: Área 1,73 m² (acentos + bancada) + 10% = 1,90 m². Cobre as 152 peças físicas com 20% de folga. Preço provisório igual ao Bleu; cotar. | I6: Proposta Portobello 05310148, 13/10/2026, arquivo sem sufixo; validade 31/10/2026
A7: Revestimentos | B7: Rejunte acrílico Pleno paredes, cor a aprovar | C7: kg | D7: 13 | E7: 89.99 | F7: =ROUND(D7*E7,2) -> 1169.87 | G7: Referência | H7: Preço do Dansk na proposta; cor Moon sugerida no catálogo. Azul escuro exige amostra/aprovação. | I7: Proposta Portobello 05310148, 13/10/2026, arquivo sem sufixo; validade 31/10/2026
A8: Revestimentos | B8: Rejunte acrílico Pleno Blanc bancada | C8: kg | D8: 1 | E8: 89.99 | F8: =ROUND(D8*E8,2) -> 89.99 | G8: Referência | H8: Preço de outra cor; confirmar preço Blanc e adequação ao tampo. | I8: Proposta Portobello 05310148, 13/10/2026, arquivo sem sufixo; validade 31/10/2026
A9: Revestimentos | B9: Argamassa colante compatível, saco 20 kg | C9: saco | D9: 0 | E9: 65 | F9: =ROUND(D9*E9,2) -> 0 | G9: Contratado | H9: Fornecida pela empreiteira (contrato fechado). Referência de consumo: 5 kg/m² × 18,68 m² ≈ 93 kg; produto compatível com a impermeabilização. | I9: Estimativa de planejamento; substituir por cotação de instalador em São Paulo
A10: Revestimentos | B10: Espaçadores 2 mm, pacote 500 | C10: pct | D10: 4 | E10: 25 | F10: =ROUND(D10*E10,2) -> 100 | G10: Estimativa | I10: Estimativa de planejamento; substituir por cotação de instalador em São Paulo
A11: Revestimentos | B11: Selante sanitário neutro compatível, 280 ml | C11: un | D11: 4 | E11: 45 | F11: =ROUND(D11*E11,2) -> 180 | G11: Estimativa | H11: Encontros, louça e perímetros; não substituir rejunte rígido em junta de movimento. | I11: Estimativa de planejamento; substituir por cotação de instalador em São Paulo
A12: Revestimentos | B12: Perfis de acabamento: topo do revestimento a 2.353 mm e bordas/cantos | C12: m | D12: 13 | E12: 65 | F12: =ROUND(D12*E12,2) -> 845 | G12: Estimativa | H12: Topo: 8,02 m (perímetro das paredes P1–P6) + 4 m de bordas e cantos; perfil reto inox/alumínio para borda de peça de 9 mm. Cantos a 45° dependem de ensaio de corte. | I12: Estimativa de planejamento; substituir por cotação de instalador em São Paulo
A13: Louças e metais | B13: Cuba Ametista 16 branca Duramatt | C13: un | D13: 1 | E13: 1557.9 | F13: =ROUND(D13*E13,2) -> 1557.9 | G13: Preço web | H13: Confirmar estoque e válvula inclusa antes de comprar. | I13: https://bellobanho.com.br/produtos/cuba-de-apoio-ametista-16-duramatt-branca-1dfq0/
A14: Louças e metais | B14: Bica de parede aço escovado 200 mm | C14: un | D14: 1 | E14: 445.69 | F14: =ROUND(D14*E14,2) -> 445.69 | G14: Referência | H14: Alternativa funcional para dois registros; anúncio tem título aço e descrição preto. Confirmar SKU/acabamento. | I14: https://www.leroymerlin.com.br/bica-para-banheira-aco-escovado_1572794948
A15: Louças e metais | B15: Registros Round acabamentos quente/frio | C15: un | D15: 2 | E15: 380 | F15: =ROUND(D15*E15,2) -> 760 | G15: Estimativa | H15: Modelo SKP não identifica SKU de compra. Preço provisório; duas bases compatíveis incluídas abaixo. | I15: Estimativa de planejamento; substituir por cotação de instalador em São Paulo
A16: Louças e metais | B16: Bases completas para misturador de parede 3 furos | C16: cj | D16: 1 | E16: 450 | F16: =ROUND(D16*E16,2) -> 450 | G16: Estimativa | H16: Não adaptar cegamente a Royale monocomando. Conjunto de bases, união de mistura e bica deve ser homologado junto. | I16: Estimativa de planejamento; substituir por cotação de instalador em São Paulo
A17: Louças e metais | B17: Bracci Aria B09048BN acabamento chuveiro | C17: un | D17: 1 | E17: 685.17 | F17: =ROUND(D17*E17,2) -> 685.17 | G17: Preço web | H17: Acabamento apenas: confirmar base DECA exata / conversor DOCOL. | I17: https://www.bracci.com.br/products/acabamento-monoc-chuveiro-aria-aco-escovado
A18: Louças e metais | B18: Base monocomando chuveiro compatível | C18: un | D18: 1 | E18: 450 | F18: =ROUND(D18*E18,2) -> 450 | G18: Estimativa | H18: Provisão; retirar se base existente comprovadamente compatível e em bom estado. | I18: Estimativa de planejamento; substituir por cotação de instalador em São Paulo
A19: Louças e metais | B19: Bracci B09052BN chuveiro teto | C19: un | D19: 1 | E19: 933.7 | F19: =ROUND(D19*E19,2) -> 933.7 | G19: Preço web | H19: Preço cartão; conferir vazão/pressão e composição do kit. | I19: https://www.bracci.com.br/products/chuveiro-de-teto-aria-aco-escovado
A20: Louças e metais | B20: Bracci B09074BN porta-papel | C20: un | D20: 1 | E20: 374.02 | F20: =ROUND(D20*E20,2) -> 374.02 | G20: Preço web | H20: Disponível em breve na consulta. Modelo BGH recolorido não muda SKU de compra. | I20: https://www.bracci.com.br/products/porta-papel-higienico-aria-aco-escovado
A21: Louças e metais | B21: Bracci B09075BN gancho | C21: un | D21: 2 | E21: 292.72 | F21: =ROUND(D21*E21,2) -> 585.44 | G21: Preço web | H21: Esgotado na loja oficial; consultar revenda. | I21: https://www.bracci.com.br/products/gancho-simples-aria-aco-escovado
A22: Louças e metais | B22: Bracci Aria toalheiro de rosto aço escovado | C22: un | D22: 1 | E22: 433.65 | F22: =ROUND(D22*E22,2) -> 433.65 | G22: Preço web | H22: Posição proposta junto à bancada, fora do giro da porta; validar interferências. | I22: https://www.bracci.com.br/products/toalheiro-rosto-aria-aco-escovado
... A26: Ralos e esgoto | B26: Sifão rígido para cuba, compatível | C26: un | D26: 1 | E26: 100 | F26: =ROUND(D26*E26,2) -> 100 | G26: Estimativa | H26: Confirmar medida real da válvula e saída existente. | I26: Estimativa de planejamento; substituir por cotação de instalador em São Paulo
A27: Ralos e esgoto | B27: Vedação/anel e fixação para reinstalar vaso | C27: cj | D27: 1 | E27: 65 | F27: =ROUND(D27*E27,2) -> 65 | G27: Estimativa | I27: Estimativa de planejamento; substituir por cotação de instalador em São Paulo
A28: Ralos e esgoto | B28: Engate flexível certificado vaso | C28: un | D28: 1 | E28: 45 | F28: =ROUND(D28*E28,2) -> 45 | G28: Estimativa | H28: Comprimento preliminar 40 cm; medir. Não embutir engate. | I28: Estimativa de planejamento; substituir por cotação de instalador em São Paulo
A29: Ralos e esgoto | B29: PVC esgoto DN50, tubos | C29: m | D29: 3 | E29: 22 | F29: =ROUND(D29*E29,2) -> 66 | G29: Estimativa | H29: Reserva, traçado/cotas de fundo não levantados; diâmetro depende dos ralos. | I29: Estimativa de planejamento; substituir por cotação de instalador em São Paulo
A30: Ralos e esgoto | B30: PVC esgoto DN40 para cuba | C30: m | D30: 2 | E30: 16 | F30: =ROUND(D30*E30,2) -> 32 | G30: Estimativa | I30: Estimativa de planejamento; substituir por cotação de instalador em São Paulo
A31: Ralos e esgoto | B31: Joelhos/luvas/junções esgoto compatíveis | C31: un | D31: 10 | E31: 15 | F31: =ROUND(D31*E31,2) -> 150 | G31: Estimativa | H31: Contagem provisória: lista final após abertura. | I31: Estimativa de planejamento; substituir por cotação de instalador em São Paulo
A32: Ralos e esgoto | B32: Adesivo, solução limpadora, anéis esgoto | C32: cj | D32: 1 | E32: 85 | F32: =ROUND(D32*E32,2) -> 85 | G32: Estimativa | I32: Estimativa de planejamento; substituir por cotação de instalador em São Paulo
A33: Água quente/fria | B33: CPVC água quente, tubos e sobra | C33: m | D33: 6 | E33: 22 | F33: =ROUND(D33*E33,2) -> 132 | G33: Estimativa | H33: Reserva de compra, não comprimento medido; diâmetro a dimensionar por pressão/vazão. | I33: Estimativa de planejamento; substituir por cotação de instalador em São Paulo
A34: Água quente/fria | B34: Isolamento térmico do ramal quente | C34: m | D34: 6 | E34: 15 | F34: =ROUND(D34*E34,2) -> 90 | G34: Estimativa | I34: Estimativa de planejamento; substituir por cotação de instalador em São Paulo
A35: Água quente/fria | B35: Tês de derivação sistema existente | C35: un | D35: 2 | E35: 25 | F35: =ROUND(D35*E35,2) -> 50 | G35: Estimativa | I35: Estimativa de planejamento; substituir por cotação de instalador em São Paulo
A36: Água quente/fria | B36: Joelhos CPVC | C36: un | D36: 8 | E36: 15 | F36: =ROUND(D36*E36,2) -> 120 | G36: Estimativa | I36: Estimativa de planejamento; substituir por cotação de instalador em São Paulo
A37: Água quente/fria | B37: Luvas/transições roscadas metálicas | C37: un | D37: 6 | E37: 25 | F37: =ROUND(D37*E37,2) -> 150 | G37: Estimativa | I37: Estimativa de planejamento; substituir por cotação de instalador em São Paulo
A38: Água quente/fria | B38: Registro de isolamento acessível | C38: un | D38: 1 | E38: 100 | F38: =ROUND(D38*E38,2) -> 100 | G38: Estimativa | I38: Estimativa de planejamento; substituir por cotação de instalador em São Paulo
A39: Água quente/fria | B39: Adesivo CPVC e consumíveis | C39: cj | D39: 1 | E39: 90 | F39: =ROUND(D39*E39,2) -> 90 | G39: Estimativa | I39: Estimativa de planejamento; substituir por cotação de instalador em São Paulo
A40: Água quente/fria | B40: Abraçadeiras, suportes e veda-rosca | C40: cj | D40: 1 | E40: 80 | F40: =ROUND(D40*E40,2) -> 80 | G40: Estimativa | I40: Estimativa de planejamento; substituir por cotação de instalador em São Paulo
A41: Impermeabilização | B41: Impermeabilizante cimentício flexível, balde 18 kg (ref. Quartzolit Tecplus Lastic) | C41: bd | D41: 3 | E41: 199.9 | F41: =ROUND(D41*E41,2) -> 599.7 | G41: Preço web | H41: 12 m² (piso, box até 2.400 mm, rodapé técnico, bancada e nicho) × cerca de 3,5 kg/m² + 10% ≈ 46 kg. Sistema, demãos e consumo a validar com fabricante e aplicador. | I41: https://www.telhanorte.com.br/impermeabilizante-quartzolit-18kg-cinza-tecplus-lastic-1619934/p
A42: Impermeabilização | B42: Tela estruturante de poliéster 73 cm × 10 m | C42: rl | D42: 1 | E42: 67.9 | F42: =ROUND(D42*E42,2) -> 67.9 | G42: Preço web | H42: Reforço em cantos, encontro piso/parede, ralos R1 e R2, flanges e passagens (cerca de 25 m de faixa). | I42: https://www.telhanorte.com.br/tela-estruturante-quartzolit-1751182/p?skuId=1751182

Sheet Quantidades
A1: Memória de compra
A2: MAXHAUS | R2 | 25/10/2026 | valores em R$ | conferir em obra
A4: Material / parâmetro | B4: Peças físicas | C4: Área revestida m² | D4: Reserva | E4: m² compra | F4: m²/cx | G4: Caixas | H4: Peças/cx | I4: Peças compradas | J4: Folga sobre peças
A5: Gouache Bleu Nuit | B5: =SUM(Paredes!H5:H19) -> 1480 | C5: =SUM(Paredes!F5:F19) -> 16.9531 | D5: 0.1 | E5: =C5*(1+D5) -> 18.64841 | F5: 0.3 | G5: =ROUNDUP(E5/F5,0) -> 63 | H5: 26 | I5: =G5*H5 -> 1638 | J5: =I5/B5-1 -> 0.10675676
A6: Gouache Nuage | B6: =SUM(Paredes!I5:I19) -> 152 | C6: =SUM(Paredes!G5:G19) -> 1.7288 | D6: 0.1 | E6: =C6*(1+D6) -> 1.90168 | F6: 0.3 | G6: =ROUNDUP(E6/F6,0) -> 7 | H6: 26 | I6: =G6*H6 -> 182 | J6: =I6/B6-1 -> 0.19736842
A9: Área piso banheiro m² | B9: 3.542305
A10: Paredes e nicho m² | B10: =SUM(Paredes!E5:E15) -> 17.604
A11: Tampo e bordas m² | B11: =SUM(Paredes!E16:E19) -> 1.0778
A12: Junta nominal mm | B12: 2
A13: Impermeabilização m² (fora do orçamento) | B13: 12
A14: Altura revestida mm (15 fiadas inteiras) | B14: 2353
A15: Compra = área revestida × (1 + reserva), arredondada para caixa fechada. Conferida contra as peças físicas: cada peça cortada consome uma peça.
A16: Calibre real do lote difere do nominal (Nuage 76,5 × 155,5): refazer a paginação com a peça medida antes de cortar.

Sheet Paredes
A1: Superfícies e peças de origem
A2: MAXHAUS | R2 | 25/10/2026 | valores em R$ | conferir em obra
A4: ID | B4: Superfície | C4: Largura mm | D4: Altura mm | E4: Área revestida m² | F4: Área Bleu m² | G4: Área Nuage m² | H4: Peças Bleu | I4: Peças Nuage | J4: Peças inteiras | K4: Peças cortadas | L4: Corte das pontas mm
A5: P1 | B5: Fundo do box / nicho | C5: 1275 | D5: 2353 | E5: 2.5994 | F5: 2.5064 | G5: 0.093 | H5: 221 | I5: 8 | J5: 173 | K5: 56 | L5: 59
A6: P2 | B6: Lateral do box / área técnica | C6: 877 | D6: 2353 | E6: 2.0636 | F6: 1.9822 | G6: 0.0814 | H6: 173 | I6: 7 | J6: 150 | K6: 30 | L6: 52.5
A7: P3 | B7: Parede da bancada e espelho | C7: 1706 | D7: 2353 | E7: 4.0142 | F7: 3.8747 | G7: 0.1395 | H7: 333 | I7: 12 | J7: 315 | K7: 30 | L7: 43.5
A8: P4 | B8: Parede da porta | C8: 2583 | D8: 2353 | E8: 4.4858 | F8: 4.2998 | G8: 0.186 | H8: 374 | I8: 16 | J8: 337 | K8: 53 | L8: 58.5
A9: P5 | B9: Parede do vaso sanitário | C9: 1427 | D9: 2353 | E9: 3.3577 | F9: 3.2299 | G9: 0.1279 | H9: 274 | I9: 11 | J9: 255 | K9: 30 | L9: 58
A10: P6 | B10: Retorno da área técnica | C10: 150 | D10: 2353 | E10: 0.3529 | F10: 0.3529 | G10: 0 | H10: 30 | I10: 0 | J10: 15 | K10: 15 | L10: 73
A11: N1 | B11: Nicho / fundo | C11: 1000 | D11: 400 | E11: 0.4 | F11: 0.3768 | G11: 0.0232 | H11: 37 | I11: 2 | J11: 13 | K11: 26 | L11: —
A12: N2 | B12: Nicho / lateral esquerda | C12: 118 | D12: 400 | E12: 0.0472 | F12: 0.0472 | G12: 0 | H12: 6 | I12: 0 | J12: 1 | K12: 5 | L12: —
A13: N3 | B13: Nicho / lateral direita | C13: 118 | D13: 400 | E13: 0.0472 | F13: 0.0472 | G13: 0 | H13: 6 | I13: 0 | J13: 1 | K13: 5 | L13: —
A14: N4 | B14: Nicho / base | C14: 1000 | D14: 118 | E14: 0.118 | F14: 0.118 | G14: 0 | H14: 13 | I14: 0 | J14: 0 | K14: 13 | L14: —
A15: N5 | B15: Nicho / teto | C15: 1000 | D15: 118 | E15: 0.118 | F15: 0.118 | G15: 0 | H15: 13 | I15: 0 | J15: 0 | K15: 13 | L15: —
A16: B1 | B16: Bancada / tampo | C16: 1650 | D16: 530 | E16: 0.8745 | F16: 0 | G16: 0.8745 | H16: 0 | I16: 77 | J16: 60 | K16: 17 | L16: —
A17: B2 | B17: Bancada / borda frontal | C17: 1650 | D17: 75 | E17: 0.1237 | F17: 0 | G17: 0.1237 | H17: 0 | I17: 11 | J17: 10 | K17: 1 | L17: —
A18: B3 | B18: Bancada / borda sul | C18: 530 | D18: 75 | E18: 0.0398 | F18: 0 | G18: 0.0398 | H18: 0 | I18: 4 | J18: 3 | K18: 1 | L18: —
A19: B4 | B19: Bancada / borda norte | C19: 530 | D19: 75 | E19: 0.0398 | F19: 0 | G19: 0.0398 | H19: 0 | I19: 4 | J19: 3 | K19: 1 | L19: —
A21: R2: paredes até 2.353 mm (15 fiadas inteiras), pontas simétricas no eixo, nicho e porta preservados. Nicho mantém 1000 × 400 × 118 mm. Área Nuage = acentos (peça 75 × 155) + bancada.

Sheet Premissas
A1: Condições de uso e fontes
A2: MAXHAUS | R2 | 25/10/2026 | valores em R$ | conferir em obra
A4: Tema | B4: Critério / decisão
A5: Status | B5: Caderno de coordenação: não liberado para obra antes da conferência de campo e validação do responsável técnico.
A6: Projeto | B6: R47; paredes Bleu Nuit com detalhes Nuage e tampo Nuage 7,5 × 15,5 cm. Paginação R2 no caderno técnico R1.
A7: Contagem | B7: Peças e recortes em Mapa_pecas_recortes.csv. Não somar área de cada fragmento: coluna de área é da peça de origem.
A8: Preços | B8: Consultados em 25/10/2026; frete e estoque a confirmar; preços de planejamento não são proposta de fornecedor.
A9: Proposta Portobello | B9: 05310148 de 13/10/2026; válida até 31/10/2026. Bleu Nuit 339,99/m². Não somar alternativas Terralma nem produtos da sala.
A10: Rejunte | B10: 2 mm solicitado; catálogo indica 1,5 mm. Acrílico azul escuro comercial não confirmado; aprovar amostra/SKU, não comprar como Dansk.
A11: Calibre | B11: Nuage: tamanho de fabricação informado 76,5 × 155,5 mm; rever paginação nominal 75 × 155 antes de cortar.
A12: Tampo | B12: Altura acabada máxima 840 mm; confirmar fabricante permite revestimento em superfície horizontal.
A13: Hidráulica | B13: Diâmetros, conexões e metragens provisórios; confirmar pressão, traçado, base monocomando, capacidade do aquecedor e cotas de esgoto.
A14: Metais | B14: Bracci aço escovado, Aiello inox escovado e bica de outro fabricante não garantem identidade de tonalidade. Comparar amostras.
A15: Alternativas excluídas | B15: Royale monocomando 527,00 não somada com conjunto bica + 2 Round. Extensor de fixação 36,75 e tubo de descarga 272,87 não somados.
... A21: Alternativa | B21: Revestir até 2.391 mm exige fiada de 36 mm em todas as paredes (107 tiras, cerca de 27 peças) e +1 caixa de Bleu Nuit.

Sheet Comparacao PB
A1: Portobello | mesma tarifa, quantidades diferentes
A2: MAXHAUS | R2 | 25/10/2026 | valores em R$ | conferir em obra
A4: Componente | B4: Proposta oficial R$ | C4: R2 R$ | D4: Diferença R$
A5: Bleu Nuit: oficial 16,20 m² / R2 18,90 m² | B5: =ROUND(16.2*B10,2) -> 5507.84 | C5: =Orcamento!F5 -> 6425.81 | D5: =C5-B5 -> 917.97
A6: Nuage: não cotado / R2 2,10 m² | B6: 0 | C6: =Orcamento!F6 -> 713.98 | D6: =C6-B6 -> 713.98
A7: Rejunte: oficial 7 kg / estudo 14 kg | B7: =ROUND(7*89.99,2) -> 629.93 | C7: =SUM(Orcamento!F7:F8) -> 1259.86 | D7: =C7-B7 -> 629.93
A8: Espaçadores, selante e perfis (argamassa: empreiteira) | B8: 0 | C8: =SUM(Orcamento!F9:F12) -> 1125 | D8: =C8-B8 -> 1125
A9: Subtotal comparável de revestimentos | B9: =SUM(B5:B8) -> 6137.77 | C9: =SUM(C5:C8) -> 9524.65 | D9: =C9-B9 -> 3386.88
A10: Bleu Nuit — preço por m² | B10: 339.99 | C10: 339.99 | D10: =C10-B10 -> 0
A13: Diferença no Bleu: 9 caixas a mais que a proposta oficial (2,70 m²), não aumento do preço por m².
A14: 63 caixas = área revestida 16,95 m² + 10%, por caixa fechada. R1 previa 70 caixas (peça cortada + 10%).
A15: A proposta oficial cotou 54 caixas. Não há comprovação de que atendam à paginação atual.
A16: Nuage: preço estimado igual ao Bleu; falta cotação específica.
A17: Rejunte: 14 kg estimados contra 7 kg oficiais; consumo e cor ainda precisam de validação.
A18: Fonte: proposta 05310148, 13/10/2026, arquivo sem sufixo, válida até 31/10/2026.
A19: A proposta também contém alternativas/sala: não integram esta comparação. Frete excluído.

Sheet Revisao R2
A1: O que mudou do R1 para o R2
A2: MAXHAUS | R2 | 25/10/2026 | valores em R$ | conferir em obra
A4: Item | B4: R1 | C4: R2 | D4: Diferença | E4: Por quê
A5: Bleu Nuit, caixas | B5: 70 | C5: =Orcamento!D5 -> 63 | D5: =C5-B5 -> -7 | E5: Compra por área + 10% e paginação com mais peças inteiras
A6: Nuage, caixas | B6: 7 | C6: =Orcamento!D6 -> 7 | D6: =C6-B6 -> 0 | E6: Mesmos 152 acentos e bancada
A7: Peças físicas Bleu | B7: 1632 | C7: =Quantidades!B5 -> 1480 | D7: =C7-B7 -> -152 | E7: Sem fiada de 36 mm no topo e com pontas simétricas
A8: Peças físicas Nuage | B8: 152 | C8: =Quantidades!B6 -> 152 | D8: =C8-B8 -> 0
A9: Perfis de acabamento, m | B9: 4 | C9: =Orcamento!D12 -> 13 | D9: =C9-B9 -> 9 | E9: Perfil no topo do revestimento (8,02 m)
A10: Argamassa colante, R$ | B10: 325 | C10: =Orcamento!F9 -> 0 | D10: =C10-B10 -> -325 | E10: Passa para a empreiteira (já contratada)
A11: Revestimentos, R$ | B11: 9978.63 | C11: =Resumo!B5 -> 9524.65 | D11: =C11-B11 -> -453.98
A12: Impermeabilização, R$ | B12: 0 | C12: =Resumo!B9 -> 667.6 | D12: =C12-B12 -> 667.6 | E12: Incluída no R2: 3 baldes de 18 kg e 1 rolo de tela
A13: Subtotal, R$ | B13: 20023.85 | C13: =Resumo!B10 -> 20237.47 | D13: =C13-B13 -> 213.62
A14: Total com contingência, R$ | B14: 23027.43 | C14: =Resumo!B13 -> 23273.09 | D14: =C14-B14 -> 245.6605 | E14: Contingência de 15% mantida

Sheet Sobreposicoes
A1: Itens que se sobrepõem: decisão do R2
A2: MAXHAUS | R2 | 25/10/2026 | valores em R$ | conferir em obra
A4: Função | B4: Opção mantida | C4: R$ mantido | D4: Opção descartada | E4: R$ descartado | F4: Por quê
A5: Ralo linear do box | B5: Ralo linear 720 mm completo | C5: =Orcamento!F24 -> 450 | D5: Ralo linear 600 × 90 mm do link | E5: 199 | F5: Projeto pede 720 mm. O de 600 mm não atende à medida e tem menor valor: descartado.
A6: Misturador da bancada | B6: Bica 200 mm + 2 registros Round + bases 3 furos | C6: =Orcamento!F14+Orcamento!F15+Orcamento!F16 -> 1655.69 | D6: Royale monocomando 21 cm | E6: 527 | F6: O modelo desenha bica e dois comandos (3 furos). Royale é monocomando de 2 furos: não atende e tem menor valor.
A7: Ligação do vaso | B7: Engate flexível certificado | C7: =Orcamento!F28 -> 45 | D7: Tubo de ligação 1½" | E7: 272.87 | F7: Vaso com caixa acoplada: o tubo de 1½" é para válvula de descarga e não atende. Mantido o engate, mesmo com valor menor.
A8: Fixação da torneira | B8: Fixação do gabarito do fabricante | C8: 0 | D8: Rosca longa 12 cm | E8: 36.75 | F8: Só comprar se o gabarito real exigir. Fora do orçamento.
A9: Argamassa colante | B9: Empreiteira (contratada) | C9: =Orcamento!F9 -> 0 | D9: Argamassa no orçamento de materiais | E9: 325 | F9: Fornecida pela empreiteira: não somar duas vezes.
A10: Toalheiros | B10: Aiello térmico + Bracci de rosto | C10: =Orcamento!F22+Orcamento!F23 -> 1818.3 | D10: — | E10: 0 | F10: Não é sobreposição: o térmico é para toalha de banho junto ao box; o de rosto fica junto à bancada. Se quiser um só, sai o Bracci (−R$ 433,65).
